ketacli/__init__.py
ketacli/__main__.py
ketacli/ketacli.py
ketacli/charts/audit.yaml
ketacli/charts/infra-host.yaml
ketacli/charts/k8s-monitor.yaml
ketacli/charts/monitor.yaml
ketacli/plugins/__init__.py
ketacli/plugins/ai_search.py
ketacli/plugins/asset.py
ketacli/plugins/auth.py
ketacli/plugins/config.py
ketacli/plugins/data.py
ketacli/plugins/interactive.py
ketacli/plugins/metric.py
ketacli/plugins/mock.py
ketacli/plugins/search.py
ketacli/plugins/visualization.py
ketacli/sdk/__init__.py
ketacli/sdk/converters.py
ketacli/sdk/util.py
ketacli/sdk/ai/__init__.py
ketacli/sdk/ai/client.py
ketacli/sdk/ai/config.py
ketacli/sdk/ai/examples.py
ketacli/sdk/ai/function_call.py
ketacli/sdk/ai/tool_output_compressor.py
ketacli/sdk/ai/validators.py
ketacli/sdk/ai/functions/__init__.py
ketacli/sdk/ai/functions/asset_functions.py
ketacli/sdk/ai/functions/data_functions.py
ketacli/sdk/ai/functions/docs_functions.py
ketacli/sdk/ai/functions/script_functions.py
ketacli/sdk/ai/functions/search_functions.py
ketacli/sdk/ai/functions/visualization_functions.py
ketacli/sdk/ai/prompts/log_search_syntax.md
ketacli/sdk/ai/prompts/metric_search_syntax.md
ketacli/sdk/ai/prompts/system.md
ketacli/sdk/ai/skills/__init__.py
ketacli/sdk/ai/skills/loader.py
ketacli/sdk/ai/skills/models.py
ketacli/sdk/ai/skills/registry.py
ketacli/sdk/ai/skills/runner.py
ketacli/sdk/ai/skills/selector.py
ketacli/sdk/ai/skills/examples/k8s资源巡检.yaml
ketacli/sdk/ai/skills/examples/k8s资源查询.yaml
ketacli/sdk/ai/skills/examples/仓库数据分析.yaml
ketacli/sdk/ai/skills/examples/执行本地命令.yaml
ketacli/sdk/ai/skills/examples/指标计算.yaml
ketacli/sdk/ai/skills/examples/日志搜索技能.yaml
ketacli/sdk/ai/skills/examples/查阅文档.yaml
ketacli/sdk/ai/skills/examples/模拟数据.yaml
ketacli/sdk/ai/skills/examples/自巡检.yaml
ketacli/sdk/ai/skills/examples/资源列出.yaml
ketacli/sdk/ai/skills/examples/资源创建.yaml
ketacli/sdk/base/__init__.py
ketacli/sdk/base/client.py
ketacli/sdk/base/config.py
ketacli/sdk/base/getch.py
ketacli/sdk/base/search.py
ketacli-1.4.2.dist-info/METADATA
ketacli-1.4.2.dist-info/WHEEL
ketacli-1.4.2.dist-info/entry_points.txt
ketacli-1.4.2.dist-info/top_level.txt
ketacli-1.4.2.dist-info/RECORD
