Metadata-Version: 2.4
Name: ketacli
Version: 1.4.2
Summary: KetaDB Client
Home-page: https://xishuhq.com
Author: lvheyang
Author-email: cuiwenzheng@ymail.com
Requires-Python: >=3.8
Requires-Dist: requests~=2.31.0
Requires-Dist: prettytable~=3.10.0
Requires-Dist: pyyaml~=6.0.1
Requires-Dist: mando~=0.7.1
Requires-Dist: argcomplete~=3.3.0
Requires-Dist: faker~=24.11.0
Requires-Dist: jinja2~=3.1.3
Requires-Dist: rich>=13.7.1
Requires-Dist: plotext~=5.2.8
Requires-Dist: textual[syntax]>=0.86.2
Requires-Dist: pyperclip~=1.8.2
Requires-Dist: textual-plotext~=1.0.1
Requires-Dist: setuptools>=65.0.0
Requires-Dist: jsonpath_ng~=1.7.0
Requires-Dist: aiohttp>=3.12.15
Requires-Dist: textual-serve>=1.1.2
Dynamic: author
Dynamic: author-email
Dynamic: home-page
